{"cameraMode":{"drawMode":0,"name":"Shaded","section":"Shading Mode"},"sceneLighting":true,"audioPlay":false,"sceneViewState":{"showFog":true,"showMaterialUpdate":false,"showSkybox":true,"showFlares":true,"showImageEffects":true,"showParticleSystems":true},"in2DMode":false,"pivot":{"x":1182.3369140625,"y":470.3764343261719,"z":-113.99830627441406},"rotation":{"x":-0.006303882226347923,"y":0.042583007365465167,"z":-0.00026895353221334517,"w":-0.99907386302948},"size":178.09869384765626,"orthographic":false}